Metadata-Version: 1.0
Name: flask-oidc-validator
Version: 1.2
Summary: A flask-oidc to validate IdToken for python 
Home-page: https://github.com/785321021/oidc-client-validate.git
Author: lixin159
Author-email: 785321021@qq.com
License: MIT
Keywords: flask-oidc
Platform: UNKNOWN
